gobspy/__init__.py
gobspy/lang/__init__.py
gobspy/lang/exceptions.py
gobspy/lang/i18n.py
gobspy/lang/preprocessor.py
gobspy/lang/state.py
gobspy/lang/utils.py
gobspy/lang/board/__init__.py
gobspy/lang/board/basic.py
gobspy/lang/board/fmt_gbb.py
gobspy/lang/board/fmt_gbt.py
gobspy/lang/board/fmt_html.py
gobspy/lang/board/fmt_json.py
gobspy/lang/board/formats.py
gobspy/lang/builtins/__init__.py
gobspy/lang/builtins/builtins.py
gobspy/lang/builtins/types/__init__.py
gobspy/lang/builtins/types/color.py
gobspy/lang/builtins/types/direction.py
gobspy/lang/builtins/types/enum.py
gobspy/tests/__init__.py
gobspy/tests/builtins/__init__.py
gobspy/tests/builtins/types/__init__.py
gobspy/tests/builtins/types/test_colors.py
gobspy/tests/builtins/types/test_directions.py
gobspy-0.1.5.dist-info/DESCRIPTION.rst
gobspy-0.1.5.dist-info/METADATA
gobspy-0.1.5.dist-info/RECORD
gobspy-0.1.5.dist-info/WHEEL
gobspy-0.1.5.dist-info/entry_points.txt
gobspy-0.1.5.dist-info/metadata.json
gobspy-0.1.5.dist-info/top_level.txt
